{
  "@schemaVersion" : "1.0",
  "name" : "kibble\\kibble-sdsm",
  "variables" : [ "kibble/api/handler.py", "kibble/api/pages/account.py", "kibble/api/pages/bio/bio.py", "kibble/api/pages/bio/newtimers.py", "kibble/api/pages/bio/trends.py", "kibble/api/pages/ci/queue.py", "kibble/api/pages/ci/status.py", "kibble/api/pages/ci/top-buildcount.py", "kibble/api/pages/ci/top-buildtime.py", "kibble/api/pages/code/changes.py", "kibble/api/pages/code/commits.py", "kibble/api/pages/code/committers.py", "kibble/api/pages/code/evolution.py", "kibble/api/pages/code/pony-timeseries.py", "kibble/api/pages/code/pony.py", "kibble/api/pages/code/relationships.py", "kibble/api/pages/code/retention.py", "kibble/api/pages/code/sloc.py", "kibble/api/pages/code/top-commits.py", "kibble/api/pages/code/top-sloc.py", "kibble/api/pages/code/trends.py", "kibble/api/pages/filters.py", "kibble/api/pages/forum/actors.py", "kibble/api/pages/forum/creators.py", "kibble/api/pages/forum/issues.py", "kibble/api/pages/forum/responders.py", "kibble/api/pages/forum/top-count.py", "kibble/api/pages/forum/top.py", "kibble/api/pages/forum/trends.py", "kibble/api/pages/issue/actors.py", "kibble/api/pages/issue/age.py", "kibble/api/pages/issue/closers.py", "kibble/api/pages/issue/issues.py", "kibble/api/pages/issue/openers.py", "kibble/api/pages/issue/pony-timeseries.py", "kibble/api/pages/issue/relationships.py", "kibble/api/pages/issue/retention.py", "kibble/api/pages/issue/top-count.py", "kibble/api/pages/issue/top.py", "kibble/api/pages/issue/trends.py", "kibble/api/pages/mail/keyphrases.py", "kibble/api/pages/mail/map.py", "kibble/api/pages/mail/mood-timeseries.py", "kibble/api/pages/mail/mood.py", "kibble/api/pages/mail/pony-timeseries.py", "kibble/api/pages/mail/relationships.py", "kibble/api/pages/mail/retention.py", "kibble/api/pages/mail/timeseries-single.py", "kibble/api/pages/mail/timeseries.py", "kibble/api/pages/mail/top-authors.py", "kibble/api/pages/mail/top-topics.py", "kibble/api/pages/mail/trends.py", "kibble/api/pages/org/contributors.py", "kibble/api/pages/org/list.py", "kibble/api/pages/org/members.py", "kibble/api/pages/org/sourcetypes.py", "kibble/api/pages/org/trends.py", "kibble/api/pages/session.py", "kibble/api/pages/sources.py", "kibble/api/pages/verify.py", "kibble/api/pages/views.py", "kibble/api/pages/widgets.py", "kibble/api/pages/__init__.py", "kibble/api/plugins/database.py", "kibble/api/plugins/openapi.py", "kibble/api/plugins/session.py", "kibble/api/yaml/openapi/combine.py", "kibble/docs/source/conf.py", "kibble/setup/makeaccount.py", "kibble/setup/setup.py" ],
  "cells" : [ {
    "src" : 0,
    "dest" : 64,
    "values" : {
      "P1" : 4.0
    }
  }, {
    "src" : 0,
    "dest" : 65,
    "values" : {
      "P1" : 3.0
    }
  }, {
    "src" : 1,
    "dest" : 65,
    "values" : {
      "P1" : 14.0
    }
  }, {
    "src" : 1,
    "dest" : 63,
    "values" : {
      "P1" : 5.0
    }
  }, {
    "src" : 2,
    "dest" : 65,
    "values" : {
      "P1" : 11.0
    }
  }, {
    "src" : 2,
    "dest" : 63,
    "values" : {
      "P1" : 6.0
    }
  }, {
    "src" : 3,
    "dest" : 65,
    "values" : {
      "P1" : 12.0
    }
  }, {
    "src" : 3,
    "dest" : 63,
    "values" : {
      "P1" : 7.0
    }
  }, {
    "src" : 4,
    "dest" : 65,
    "values" : {
      "P1" : 8.0
    }
  }, {
    "src" : 5,
    "dest" : 65,
    "values" : {
      "P1" : 8.0
    }
  }, {
    "src" : 5,
    "dest" : 63,
    "values" : {
      "P1" : 2.0
    }
  }, {
    "src" : 6,
    "dest" : 65,
    "values" : {
      "P1" : 8.0
    }
  }, {
    "src" : 6,
    "dest" : 63,
    "values" : {
      "P1" : 2.0
    }
  }, {
    "src" : 7,
    "dest" : 65,
    "values" : {
      "P1" : 8.0
    }
  }, {
    "src" : 7,
    "dest" : 63,
    "values" : {
      "P1" : 2.0
    }
  }, {
    "src" : 8,
    "dest" : 65,
    "values" : {
      "P1" : 8.0
    }
  }, {
    "src" : 8,
    "dest" : 63,
    "values" : {
      "P1" : 2.0
    }
  }, {
    "src" : 9,
    "dest" : 65,
    "values" : {
      "P1" : 8.0
    }
  }, {
    "src" : 9,
    "dest" : 63,
    "values" : {
      "P1" : 2.0
    }
  }, {
    "src" : 10,
    "dest" : 65,
    "values" : {
      "P1" : 8.0
    }
  }, {
    "src" : 10,
    "dest" : 63,
    "values" : {
      "P1" : 2.0
    }
  }, {
    "src" : 11,
    "dest" : 65,
    "values" : {
      "P1" : 10.0
    }
  }, {
    "src" : 11,
    "dest" : 63,
    "values" : {
      "P1" : 5.0
    }
  }, {
    "src" : 12,
    "dest" : 65,
    "values" : {
      "P1" : 9.0
    }
  }, {
    "src" : 12,
    "dest" : 63,
    "values" : {
      "P1" : 4.0
    }
  }, {
    "src" : 13,
    "dest" : 65,
    "values" : {
      "P1" : 9.0
    }
  }, {
    "src" : 13,
    "dest" : 63,
    "values" : {
      "P1" : 2.0
    }
  }, {
    "src" : 14,
    "dest" : 65,
    "values" : {
      "P1" : 9.0
    }
  }, {
    "src" : 14,
    "dest" : 63,
    "values" : {
      "P1" : 2.0
    }
  }, {
    "src" : 15,
    "dest" : 65,
    "values" : {
      "P1" : 11.0
    }
  }, {
    "src" : 15,
    "dest" : 63,
    "values" : {
      "P1" : 7.0
    }
  }, {
    "src" : 16,
    "dest" : 65,
    "values" : {
      "P1" : 9.0
    }
  }, {
    "src" : 16,
    "dest" : 63,
    "values" : {
      "P1" : 3.0
    }
  }, {
    "src" : 17,
    "dest" : 65,
    "values" : {
      "P1" : 8.0
    }
  }, {
    "src" : 17,
    "dest" : 63,
    "values" : {
      "P1" : 2.0
    }
  }, {
    "src" : 18,
    "dest" : 65,
    "values" : {
      "P1" : 8.0
    }
  }, {
    "src" : 18,
    "dest" : 63,
    "values" : {
      "P1" : 2.0
    }
  }, {
    "src" : 19,
    "dest" : 65,
    "values" : {
      "P1" : 8.0
    }
  }, {
    "src" : 19,
    "dest" : 63,
    "values" : {
      "P1" : 2.0
    }
  }, {
    "src" : 20,
    "dest" : 65,
    "values" : {
      "P1" : 9.0
    }
  }, {
    "src" : 20,
    "dest" : 63,
    "values" : {
      "P1" : 3.0
    }
  }, {
    "src" : 21,
    "dest" : 65,
    "values" : {
      "P1" : 4.0
    }
  }, {
    "src" : 21,
    "dest" : 63,
    "values" : {
      "P1" : 2.0
    }
  }, {
    "src" : 22,
    "dest" : 65,
    "values" : {
      "P1" : 8.0
    }
  }, {
    "src" : 22,
    "dest" : 63,
    "values" : {
      "P1" : 2.0
    }
  }, {
    "src" : 23,
    "dest" : 65,
    "values" : {
      "P1" : 10.0
    }
  }, {
    "src" : 23,
    "dest" : 63,
    "values" : {
      "P1" : 5.0
    }
  }, {
    "src" : 24,
    "dest" : 65,
    "values" : {
      "P1" : 8.0
    }
  }, {
    "src" : 24,
    "dest" : 63,
    "values" : {
      "P1" : 2.0
    }
  }, {
    "src" : 25,
    "dest" : 65,
    "values" : {
      "P1" : 10.0
    }
  }, {
    "src" : 25,
    "dest" : 63,
    "values" : {
      "P1" : 5.0
    }
  }, {
    "src" : 26,
    "dest" : 65,
    "values" : {
      "P1" : 10.0
    }
  }, {
    "src" : 26,
    "dest" : 63,
    "values" : {
      "P1" : 5.0
    }
  }, {
    "src" : 27,
    "dest" : 65,
    "values" : {
      "P1" : 8.0
    }
  }, {
    "src" : 27,
    "dest" : 63,
    "values" : {
      "P1" : 2.0
    }
  }, {
    "src" : 28,
    "dest" : 65,
    "values" : {
      "P1" : 9.0
    }
  }, {
    "src" : 28,
    "dest" : 63,
    "values" : {
      "P1" : 3.0
    }
  }, {
    "src" : 29,
    "dest" : 65,
    "values" : {
      "P1" : 8.0
    }
  }, {
    "src" : 29,
    "dest" : 63,
    "values" : {
      "P1" : 2.0
    }
  }, {
    "src" : 30,
    "dest" : 65,
    "values" : {
      "P1" : 8.0
    }
  }, {
    "src" : 30,
    "dest" : 63,
    "values" : {
      "P1" : 2.0
    }
  }, {
    "src" : 31,
    "dest" : 65,
    "values" : {
      "P1" : 10.0
    }
  }, {
    "src" : 31,
    "dest" : 63,
    "values" : {
      "P1" : 5.0
    }
  }, {
    "src" : 32,
    "dest" : 65,
    "values" : {
      "P1" : 8.0
    }
  }, {
    "src" : 32,
    "dest" : 63,
    "values" : {
      "P1" : 2.0
    }
  }, {
    "src" : 33,
    "dest" : 65,
    "values" : {
      "P1" : 10.0
    }
  }, {
    "src" : 33,
    "dest" : 63,
    "values" : {
      "P1" : 5.0
    }
  }, {
    "src" : 34,
    "dest" : 65,
    "values" : {
      "P1" : 9.0
    }
  }, {
    "src" : 34,
    "dest" : 63,
    "values" : {
      "P1" : 2.0
    }
  }, {
    "src" : 35,
    "dest" : 65,
    "values" : {
      "P1" : 11.0
    }
  }, {
    "src" : 35,
    "dest" : 63,
    "values" : {
      "P1" : 7.0
    }
  }, {
    "src" : 36,
    "dest" : 65,
    "values" : {
      "P1" : 9.0
    }
  }, {
    "src" : 36,
    "dest" : 63,
    "values" : {
      "P1" : 3.0
    }
  }, {
    "src" : 37,
    "dest" : 65,
    "values" : {
      "P1" : 10.0
    }
  }, {
    "src" : 37,
    "dest" : 63,
    "values" : {
      "P1" : 5.0
    }
  }, {
    "src" : 38,
    "dest" : 65,
    "values" : {
      "P1" : 8.0
    }
  }, {
    "src" : 38,
    "dest" : 63,
    "values" : {
      "P1" : 2.0
    }
  }, {
    "src" : 39,
    "dest" : 65,
    "values" : {
      "P1" : 9.0
    }
  }, {
    "src" : 39,
    "dest" : 63,
    "values" : {
      "P1" : 3.0
    }
  }, {
    "src" : 40,
    "dest" : 65,
    "values" : {
      "P1" : 8.0
    }
  }, {
    "src" : 40,
    "dest" : 63,
    "values" : {
      "P1" : 2.0
    }
  }, {
    "src" : 41,
    "dest" : 65,
    "values" : {
      "P1" : 11.0
    }
  }, {
    "src" : 41,
    "dest" : 63,
    "values" : {
      "P1" : 7.0
    }
  }, {
    "src" : 42,
    "dest" : 65,
    "values" : {
      "P1" : 9.0
    }
  }, {
    "src" : 42,
    "dest" : 63,
    "values" : {
      "P1" : 3.0
    }
  }, {
    "src" : 43,
    "dest" : 65,
    "values" : {
      "P1" : 9.0
    }
  }, {
    "src" : 43,
    "dest" : 63,
    "values" : {
      "P1" : 3.0
    }
  }, {
    "src" : 44,
    "dest" : 65,
    "values" : {
      "P1" : 9.0
    }
  }, {
    "src" : 44,
    "dest" : 63,
    "values" : {
      "P1" : 2.0
    }
  }, {
    "src" : 45,
    "dest" : 65,
    "values" : {
      "P1" : 11.0
    }
  }, {
    "src" : 45,
    "dest" : 63,
    "values" : {
      "P1" : 7.0
    }
  }, {
    "src" : 46,
    "dest" : 65,
    "values" : {
      "P1" : 9.0
    }
  }, {
    "src" : 46,
    "dest" : 63,
    "values" : {
      "P1" : 3.0
    }
  }, {
    "src" : 47,
    "dest" : 65,
    "values" : {
      "P1" : 8.0
    }
  }, {
    "src" : 47,
    "dest" : 63,
    "values" : {
      "P1" : 2.0
    }
  }, {
    "src" : 48,
    "dest" : 65,
    "values" : {
      "P1" : 8.0
    }
  }, {
    "src" : 48,
    "dest" : 63,
    "values" : {
      "P1" : 2.0
    }
  }, {
    "src" : 49,
    "dest" : 65,
    "values" : {
      "P1" : 10.0
    }
  }, {
    "src" : 49,
    "dest" : 63,
    "values" : {
      "P1" : 5.0
    }
  }, {
    "src" : 50,
    "dest" : 65,
    "values" : {
      "P1" : 8.0
    }
  }, {
    "src" : 50,
    "dest" : 63,
    "values" : {
      "P1" : 2.0
    }
  }, {
    "src" : 51,
    "dest" : 65,
    "values" : {
      "P1" : 8.0
    }
  }, {
    "src" : 51,
    "dest" : 63,
    "values" : {
      "P1" : 2.0
    }
  }, {
    "src" : 52,
    "dest" : 65,
    "values" : {
      "P1" : 9.0
    }
  }, {
    "src" : 52,
    "dest" : 63,
    "values" : {
      "P1" : 3.0
    }
  }, {
    "src" : 53,
    "dest" : 65,
    "values" : {
      "P1" : 8.0
    }
  }, {
    "src" : 53,
    "dest" : 63,
    "values" : {
      "P1" : 7.0
    }
  }, {
    "src" : 54,
    "dest" : 65,
    "values" : {
      "P1" : 17.0
    }
  }, {
    "src" : 54,
    "dest" : 63,
    "values" : {
      "P1" : 17.0
    }
  }, {
    "src" : 56,
    "dest" : 65,
    "values" : {
      "P1" : 7.0
    }
  }, {
    "src" : 56,
    "dest" : 63,
    "values" : {
      "P1" : 6.0
    }
  }, {
    "src" : 57,
    "dest" : 65,
    "values" : {
      "P1" : 15.0
    }
  }, {
    "src" : 57,
    "dest" : 63,
    "values" : {
      "P1" : 9.0
    }
  }, {
    "src" : 58,
    "dest" : 65,
    "values" : {
      "P1" : 17.0
    }
  }, {
    "src" : 58,
    "dest" : 63,
    "values" : {
      "P1" : 12.0
    }
  }, {
    "src" : 59,
    "dest" : 65,
    "values" : {
      "P1" : 4.0
    }
  }, {
    "src" : 59,
    "dest" : 63,
    "values" : {
      "P1" : 4.0
    }
  }, {
    "src" : 60,
    "dest" : 65,
    "values" : {
      "P1" : 9.0
    }
  }, {
    "src" : 60,
    "dest" : 63,
    "values" : {
      "P1" : 9.0
    }
  }, {
    "src" : 61,
    "dest" : 65,
    "values" : {
      "P1" : 1.0
    }
  }, {
    "src" : 65,
    "dest" : 63,
    "values" : {
      "P1" : 14.0
    }
  }, {
    "src" : 69,
    "dest" : 63,
    "values" : {
      "P1" : 3.0
    }
  } ]
}